{
    "os": "macOS-10.16-x86_64-i386-64bit",
    "python": "3.8.13",
    "heartbeatAt": "2023-04-03T17:22:18.305039",
    "startedAt": "2023-04-03T17:22:17.812340",
    "docker": null,
    "cuda": null,
    "args": null,
    "state": "running",
    "program": "<python with no main file>",
    "git": {
        "remote": "https://github.com/hasibzunair/learn-mlops",
        "commit": "2e0f8574e4071b455adeb21d39c695d34a35ed35"
    },
    "email": "hasibzunair@gmail.com",
    "root": "/Users/hasibzunair/Developer/learning/learn-mlops",
    "host": "Hasibs-MacBook-Pro.local",
    "username": "hasibzunair",
    "executable": "/Users/hasibzunair/anaconda3/envs/dev/bin/python",
    "cpu_count": 6,
    "cpu_count_logical": 12,
    "cpu_freq": {
        "current": 2600,
        "min": 2600,
        "max": 2600
    },
    "cpu_freq_per_core": [
        {
            "current": 2600,
            "min": 2600,
            "max": 2600
        }
    ],
    "disk": {
        "total": 465.62699127197266,
        "used": 22.157390594482422
    },
    "memory": {
        "total": 16.0
    }
}
